[
    {
        "title": "跨境通股价严重异常波动 公司称可能存在短期涨幅较大后下跌的风险",
        "time": "2024-12-05 21:47:12",
        "url": "https://www.nbd.com.cn/articles/2024-12-05/3674418.html"
    },
    {
        "title": "“港股国货彩妆第一股”毛戈平成“冻资王” 孖展额已超1700亿港元",
        "time": "2024-12-05 21:46:30",
        "url": "https://www.nbd.com.cn/articles/2024-12-05/3674315.html"
    },
    {
        "title": "金融街物业、招商积余加码，物企抢滩房产中介市场，这块“蛋糕”好分吗？",
        "time": "2024-12-05 21:45:02",
        "url": "https://www.nbd.com.cn/articles/2024-12-05/3674397.html"
    },
    {
        "title": "特斯拉Cybercab最新爆料：结构件减少六成，史上最简化车型？",
        "time": "2024-12-05 21:45:00",
        "url": "https://tech.ifeng.com/c/8f4eA7iyaDF"
    },
    {
        "title": "两只基金单日涨超6%，均为文娱传媒主题",
        "time": "2024-12-05 21:44:27",
        "url": "https://www.nbd.com.cn/articles/2024-12-05/3674405.html"
    },
    {
        "title": "一汽解放6DV超级工厂落成投产，首款氢气发动机正式发布",
        "time": "2024-12-05 21:37:22",
        "url": "https://www.jiemian.com/article/12082541.html"
    },
    {
        "title": "上周美国首次申请失业救济人数22.4万人，高于预期",
        "time": "2024-12-05 21:30:14",
        "url": "https://wallstreetcn.com/articles/3736209"
    },
    {
        "title": "普洛斯中国数据中心业务联席总裁郭仁声：数据中心的运营能力与服务水平，是资本获得长",
        "time": "2024-12-05 21:28:03",
        "url": "https://www.nbd.com.cn/articles/2024-12-05/3674360.html"
    },
    {
        "title": "华尔街出手，大手笔布局A股，还上杠杆！多位大佬看好中国股市：这是全球最便宜的股票市",
        "time": "2024-12-05 21:27:32",
        "url": "https://www.nbd.com.cn/articles/2024-12-05/3674402.html"
    },
    {
        "title": "消息传来！“美国驻日太空军”宣告成立，指挥所设在东京的美军基地：既搜集情报，又参",
        "time": "2024-12-05 21:27:18",
        "url": "https://www.nbd.com.cn/articles/2024-12-05/3674401.html"
    },
    {
        "title": "热搜第一！网购“100%山羊绒衫”竟是“0羊绒”，网友：188元不可能买到纯羊绒",
        "time": "2024-12-05 21:27:02",
        "url": "https://www.nbd.com.cn/articles/2024-12-05/3674400.html"
    },
    {
        "title": "中国宝武与海尔集团签署全面深化战略合作协议",
        "time": "2024-12-05 21:23:47",
        "url": "https://www.jiemian.com/article/12082494.html"
    },
    {
        "title": "前10个月我国光伏产品“价减”而出口“量增”  光伏龙头企业再度呼吁自律",
        "time": "2024-12-05 21:23:30",
        "url": "https://www.nbd.com.cn/articles/2024-12-05/3674371.html"
    },
    {
        "title": "叙利亚反对派武装已进入叙中部城市哈马市！俄方发声！美国警告：“伊斯兰国”组织可能",
        "time": "2024-12-05 21:23:11",
        "url": "https://www.nbd.com.cn/articles/2024-12-05/3674394.html"
    },
    {
        "title": "绿城中国：前11月总合同销售额约2468亿元",
        "time": "2024-12-05 21:16:22",
        "url": "https://www.jiemian.com/article/12082482.html"
    },
    {
        "title": "市值损失1万亿，基辛格如何“带毁”英特尔？",
        "time": "2024-12-05 21:15:44",
        "url": "https://tech.ifeng.com/c/8f4brLYo676"
    },
    {
        "title": "报道：英伟达Blackwell计划在美国本土完成制造",
        "time": "2024-12-05 21:11:04",
        "url": "https://wallstreetcn.com/articles/3736207"
    },
    {
        "title": "我国首枚可回收火箭“朱雀三号”有望明年运营，已完成 10 公里级垂直起降飞行试验",
        "time": "2024-12-05 21:13:13",
        "url": "https://www.ithome.com/0/815/659.htm"
    },
    {
        "title": "华为发布 SDK 生态繁荣伙伴支持计划，信通院全国 SDK 管理服务平台鸿蒙专区上线",
        "time": "2024-12-05 21:13:02",
        "url": "https://www.ithome.com/0/815/657.htm"
    },
    {
        "title": "OpenHarmony 社区：11 月新增 51 款产品通过兼容性测评，社区生态伙伴发展至 391 家",
        "time": "2024-12-05 21:09:40",
        "url": "https://www.ithome.com/0/815/656.htm"
    },
    {
        "title": "鸿海宣布将加强医疗技术投入、布局护理机器人领域",
        "time": "2024-12-05 21:05:33",
        "url": "https://www.ithome.com/0/815/655.htm"
    },
    {
        "title": "汇丰任命美国业务CEO，环球私人银行及财富管理行政总裁诗文慧将离职",
        "time": "2024-12-05 21:05:12",
        "url": "https://www.jiemian.com/article/12082454.html"
    },
    {
        "title": "美股指数期货窄幅震荡，欧股延续涨势，法股上涨，比特币突破10万美元",
        "time": "2024-12-05 21:03:21",
        "url": "https://wallstreetcn.com/articles/3736135"
    },
    {
        "title": "2024贺岁档新片总票房破8亿",
        "time": "2024-12-05 21:02:21",
        "url": "https://www.jiemian.com/article/12082440.html"
    },
    {
        "title": "全国产不容易！李楠评价华为Mate 70：消费者感受不到制程落后",
        "time": "2024-12-05 20:58:00",
        "url": "https://tech.ifeng.com/c/8f4aT5Zqm8r"
    },
    {
        "title": "蔚来与万事达卡签署战略合作协议，探索搭建车内支付功能",
        "time": "2024-12-05 20:57:49",
        "url": "https://www.ithome.com/0/815/654.htm"
    },
    {
        "title": "如何提高生物药专利转化率？深圳理工大学药学院院长陈有海：最好的方式是校企融合，聚",
        "time": "2024-12-05 20:57:32",
        "url": "https://www.nbd.com.cn/articles/2024-12-05/3673998.html"
    },
    {
        "title": "专访中国银行海南省分行副行长张正强：EF账户为优质企业的跨境结算注入新动能",
        "time": "2024-12-05 20:56:24",
        "url": "https://www.nbd.com.cn/articles/2024-12-05/3674354.html"
    },
    {
        "title": "蔚来与万事达卡签署战略合作协议，将探索搭建车内支付功能",
        "time": "2024-12-05 20:55:45",
        "url": "https://www.jiemian.com/article/12082425.html"
    },
    {
        "title": "a16z联合创始人安德里森据悉帮助马斯克将领导的“政府效率部”招聘员工",
        "time": "2024-12-05 20:54:29",
        "url": "https://www.jiemian.com/article/12082415.html"
    },
    {
        "title": "ARRI 发布新一代 65mm 格式摄影机 ALEXA 265，计划 2025 年初量产",
        "time": "2024-12-05 20:54:27",
        "url": "https://www.ithome.com/0/815/653.htm"
    },
    {
        "title": "HashKey集团首席运营官翁晓奇将于年底离职",
        "time": "2024-12-05 20:53:33",
        "url": "https://www.jiemian.com/article/12082410.html"
    },
    {
        "title": "涉嫌内幕交易、短线交易获利54.92万元 甬金股份实控人或被处584.58万元罚款",
        "time": "2024-12-05 20:50:38",
        "url": "https://www.nbd.com.cn/articles/2024-12-05/3674355.html"
    },
    {
        "title": "比亚迪赵长江：腾势 Z9 试驾车陆续到店，12 月 6 日开启交付",
        "time": "2024-12-05 20:50:20",
        "url": "https://www.ithome.com/0/815/651.htm"
    },
    {
        "title": "订单量将超 150 万台，禾赛激光雷达获长安汽车旗下多个品牌独家量产定点",
        "time": "2024-12-05 20:47:52",
        "url": "https://www.ithome.com/0/815/650.htm"
    },
    {
        "title": "从“小白”成长为新能源产业高地，这个城市做对了什么？",
        "time": "2024-12-05 20:44:07",
        "url": "https://www.nbd.com.cn/articles/2024-12-05/3674093.html"
    },
    {
        "title": "马斯克的星链用到飞机上了，中国版正奋起直追",
        "time": "2024-12-05 20:43:37",
        "url": "https://tech.ifeng.com/c/8f47jzWNZPX"
    },
    {
        "title": "历史性突破10万美元，比特币到底还能涨多久？",
        "time": "2024-12-05 20:43:32",
        "url": "https://wallstreetcn.com/articles/3736188"
    },
    {
        "title": "鸿海将布局护理机器人领域",
        "time": "2024-12-05 20:43:12",
        "url": "https://www.jiemian.com/article/12082363.html"
    },
    {
        "title": "首款 PCIe 5.0 SSD 笔记本：联想 ThinkPad X1 Carbon Aura 2025 AI 元启版发布，15999 元起",
        "time": "2024-12-05 20:39:22",
        "url": "https://www.ithome.com/0/815/649.htm"
    },
    {
        "title": "2025 电竞世界杯明夏回归，《DOTA2》《街霸 6》等项目官宣",
        "time": "2024-12-05 20:39:06",
        "url": "https://www.ithome.com/0/815/648.htm"
    },
    {
        "title": "特朗普提名史上最年轻NASA局长！高中辍学成亿万富翁、马斯克密友、上过两次太空",
        "time": "2024-12-05 20:36:23",
        "url": "https://wallstreetcn.com/articles/3736178"
    },
    {
        "title": "金表商西普尼三度冲刺IPO，曾在新三板“两进两出”",
        "time": "2024-12-05 20:36:08",
        "url": "https://wallstreetcn.com/articles/3736203"
    },
    {
        "title": "CNOA 城市领航覆盖至全国，23 / 24 款比亚迪腾势 N7 汽车获 1.8.0 / 1.5.0 内测升级",
        "time": "2024-12-05 20:35:25",
        "url": "https://www.ithome.com/0/815/647.htm"
    },
    {
        "title": "英伟达将在越南开设 AI 中心，计划收购 AI 医疗技术公司 Vinbrain",
        "time": "2024-12-05 20:32:49",
        "url": "https://www.ithome.com/0/815/646.htm"
    },
    {
        "title": "冰岛航空接收其首架空客飞机",
        "time": "2024-12-05 20:30:51",
        "url": "https://www.jiemian.com/article/12082342.html"
    },
    {
        "title": "安防芯片，正“卷”土重来",
        "time": "2024-12-05 20:30:45",
        "url": "https://36kr.com/p/3065812544988545"
    },
    {
        "title": "阿里国际在美国推出AI电商设计工具Pic Copilot",
        "time": "2024-12-05 20:24:33",
        "url": "https://www.jiemian.com/article/12082317.html"
    },
    {
        "title": "豆神“摘帽”，AI教育“杀疯”了？",
        "time": "2024-12-05 20:20:46",
        "url": "https://36kr.com/p/3065812519468804"
    },
    {
        "title": "影石 Insta360 拇指相机 GO 3S 哆啦 A 梦限定款发售：单机重约 39g、磁吸设计，2998 元",
        "time": "2024-12-05 20:20:37",
        "url": "https://www.ithome.com/0/815/645.htm"
    }
]