[
    {
        "title": "小鹏P7+AI智驾技术分享会10月24日举行，预售20.98万起",
        "time": "2024-10-21 15:33:09",
        "url": "https://tech.ifeng.com/c/8drXgNta4IG"
    },
    {
        "title": "研究人员测试新型远程操作系统，未来可遥控机器人在月球挖土",
        "time": "2024-10-21 15:10:23",
        "url": "https://www.ithome.com/0/803/886.htm"
    },
    {
        "title": "三星、联想完成业界首个 128GB CMM-D CXL 内存模块联合验证",
        "time": "2024-10-21 15:10:44",
        "url": "https://www.ithome.com/0/803/887.htm"
    },
    {
        "title": "Zara姐妹品牌Oysho将关闭天猫旗舰店",
        "time": "2024-10-21 15:10:46",
        "url": "https://www.jiemian.com/article/11856457.html"
    },
    {
        "title": "肆芃科技完成近亿元Pre-A轮融资",
        "time": "2024-10-21 15:13:30",
        "url": "https://www.jiemian.com/article/11856475.html"
    },
    {
        "title": "飞米 MINI 3 SE 无人机国行开售：245 克重量、32 分钟续航，1499 元起",
        "time": "2024-10-21 15:14:41",
        "url": "https://www.ithome.com/0/803/894.htm"
    },
    {
        "title": "获股票回购专项贷款不超过3亿元 中远海控：用好金融新工具，提升公司投资价值",
        "time": "2024-10-21 15:14:56",
        "url": "https://www.nbd.com.cn/articles/2024-10-21/3597939.html"
    },
    {
        "title": "余承东自爆明年商用L3自动驾驶，鸿蒙智行要啃新的硬骨头了？",
        "time": "2024-10-21 15:15:15.146000",
        "url": "https://36kr.com/p/3001696672494725"
    },
    {
        "title": "当前牛市第二阶段像哪次？",
        "time": "2024-10-21 15:15:35",
        "url": "https://wallstreetcn.com/articles/3730961"
    },
    {
        "title": "苹果大跌，联想赢麻，AI终于让PC市场支棱起来了？",
        "time": "2024-10-21 15:15:35.984000",
        "url": "https://36kr.com/p/3001697233826694"
    },
    {
        "title": "A500指数ETF(560610)单日成交破9亿！核心资产持续获资金青睐",
        "time": "2024-10-21 15:15:45",
        "url": "https://www.nbd.com.cn/articles/2024-10-21/3597946.html"
    },
    {
        "title": "中证1000ETF（159845）“吸金力”爆表，关注普涨后分化阶段中小盘指数演绎",
        "time": "2024-10-21 15:16:11",
        "url": "https://www.nbd.com.cn/articles/2024-10-21/3597951.html"
    },
    {
        "title": "一年内口碑大逆转，自动驾驶成旧金山旅游“打卡点”",
        "time": "2024-10-21 15:16:46",
        "url": "https://www.ithome.com/0/803/895.htm"
    },
    {
        "title": "获股票回购专项借款 山鹰国际今日股价涨停",
        "time": "2024-10-21 15:17:09",
        "url": "https://www.nbd.com.cn/articles/2024-10-21/3597945.html"
    },
    {
        "title": "3000亿，黑石正在抄底",
        "time": "2024-10-21 15:19:01.338000",
        "url": "https://36kr.com/p/3001912006949000"
    },
    {
        "title": "ETF今日收评 | 军工，芯片等ETF涨超5%，证券相关ETF跌幅居前",
        "time": "2024-10-21 15:19:22",
        "url": "https://www.nbd.com.cn/articles/2024-10-21/3597952.html"
    },
    {
        "title": "ETF基金这么“好”，为什么你却总是拿不住？",
        "time": "2024-10-21 15:19:25.200000",
        "url": "https://36kr.com/p/3001909532473480"
    },
    {
        "title": "高善文：关于促进房地产市场止跌回稳，加快建立房地产业务新模式的几点思考",
        "time": "2024-10-21 15:22:03",
        "url": "https://wallstreetcn.com/articles/3730966"
    },
    {
        "title": "一周找了五个情感陪伴AI产品聊天，我感到更空虚寂寞了？",
        "time": "2024-10-21 15:22:37.762000",
        "url": "https://36kr.com/p/3001856796144776"
    },
    {
        "title": "直播间怒怼叶珂“给我滚出互联网”，辛巴找到了流量密码？",
        "time": "2024-10-21 15:22:58.862000",
        "url": "https://36kr.com/p/3001848603866248"
    },
    {
        "title": "泰山文旅集团物业公司测试“机器狗”，冀望解决垃圾清运难题",
        "time": "2024-10-21 15:23:30",
        "url": "https://www.jiemian.com/article/11856495.html"
    },
    {
        "title": "成首个万亿美元亚洲科技公司，台积电有烦恼，也有光明的未来",
        "time": "2024-10-21 15:24:33.177000",
        "url": "https://36kr.com/p/3001718413407113"
    },
    {
        "title": "知申禾行完成数千万元天使轮融资",
        "time": "2024-10-21 15:25:24",
        "url": "https://www.jiemian.com/article/11856533.html"
    },
    {
        "title": "为什么中国要征“离岸高净值税”？",
        "time": "2024-10-21 15:25:28.406000",
        "url": "https://36kr.com/p/3001828794610567"
    },
    {
        "title": "法拉第未来举办第二汽车品牌 Logo 征集活动，获胜者最高可得“价值三万美金 FX 共创合同”",
        "time": "2024-10-21 15:27:38",
        "url": "https://www.ithome.com/0/803/898.htm"
    },
    {
        "title": "A股三大指数收涨，北证50涨超16%创新高，半导体领涨，回购增持概念股活跃，港股恒生科指跌超2%",
        "time": "2024-10-21 15:27:52",
        "url": "https://wallstreetcn.com/articles/3730948"
    },
    {
        "title": "魅族 Lucky 08 手机首次系统更新：双击电源键新增快捷打开智慧场景",
        "time": "2024-10-21 15:28:10",
        "url": "https://www.ithome.com/0/803/899.htm"
    },
    {
        "title": "欧洲投资巨头JAB收购亿滋国际所持JDE Peet's的8600万股股份",
        "time": "2024-10-21 15:28:30",
        "url": "https://www.jiemian.com/article/11856558.html"
    },
    {
        "title": "昨日路今日拆：微软Surface Duo 2手机今起正式结束生命周期",
        "time": "2024-10-21 15:30:00",
        "url": "https://tech.ifeng.com/c/8drUbdP37y9"
    },
    {
        "title": "i5-14400F + RX 7600：联想 GeekPro 台式机 16+512G 版 3955 元 3 期免息",
        "time": "2024-10-21 15:30:03",
        "url": "https://www.ithome.com/0/803/900.htm"
    },
    {
        "title": "“不想回本只想早日赎回”，基民们被冯明远的三年封基伤了心",
        "time": "2024-10-21 15:30:09.728000",
        "url": "https://36kr.com/p/3001821664129920"
    },
    {
        "title": "林园投资：考虑到A股当下面临的历史机遇，即日起将跟投比例调整至10%",
        "time": "2024-10-21 15:31:42",
        "url": "https://www.jiemian.com/article/11856586.html"
    },
    {
        "title": "中国银行：已与近百家上市公司达成股票回购增持贷款合作意向",
        "time": "2024-10-21 15:32:40",
        "url": "https://www.jiemian.com/article/11856599.html"
    },
    {
        "title": "小鹏 P7+ AI 智驾技术分享会 10 月 24 日举行，预售价 20.98 万元起",
        "time": "2024-10-21 15:32:50",
        "url": "https://www.ithome.com/0/803/901.htm"
    },
    {
        "title": "签订股票回购专项贷款合同 迈为股份：稳定市场预期，将继续加强与投资者交流",
        "time": "2024-10-21 15:32:59",
        "url": "https://www.nbd.com.cn/articles/2024-10-21/3597970.html"
    },
    {
        "title": "大盘全天宽幅震荡，中证A500ETF（159338）迎资金抢筹，今日成交额超26亿元，上市四日净",
        "time": "2024-10-21 15:33:01",
        "url": "https://www.nbd.com.cn/articles/2024-10-21/3597976.html"
    },
    {
        "title": "法拉第未来 FF 第二品牌 FX5 / FX6 车型计划“明年底前下线”：可选增程 / 纯电，2 万美元起",
        "time": "2024-10-21 15:34:18",
        "url": "https://www.ithome.com/0/803/902.htm"
    },
    {
        "title": "小米之家 4000 多家门店支持支付宝“碰一下”功能",
        "time": "2024-10-21 15:36:37",
        "url": "https://www.ithome.com/0/803/903.htm"
    },
    {
        "title": "发生了什么？午后各大指数都在回落，只有北交所继续暴涨，15天翻倍！",
        "time": "2024-10-21 15:38:20",
        "url": "https://www.nbd.com.cn/articles/2024-10-21/3597979.html"
    },
    {
        "title": "发布不到半年立打 6 折：海信 Vidda C2 至臻版 4K 激光投影仪 3882 元新低",
        "time": "2024-10-21 15:38:42",
        "url": "https://www.ithome.com/0/803/904.htm"
    },
    {
        "title": "2025 款雷克萨斯 ES 说明书曝光：外观调整，车内换装 15 英寸中控屏",
        "time": "2024-10-21 15:39:36",
        "url": "https://www.ithome.com/0/803/905.htm"
    },
    {
        "title": "华为 nova 13 系列手机四款配色海报官宣：可选洛登绿 / 羽砂紫 / 羽砂白 / 星耀黑",
        "time": "2024-10-21 15:42:59",
        "url": "https://www.ithome.com/0/803/906.htm"
    },
    {
        "title": "索尼集团和本田将在双方共同开发的新EV中引入AI智驾功能",
        "time": "2024-10-21 15:44:43",
        "url": "https://www.jiemian.com/article/11856742.html"
    },
    {
        "title": "获20亿元股票回购贷款支持 温氏股份董秘：专项贷款拓宽资金来源渠道",
        "time": "2024-10-21 15:45:48",
        "url": "https://www.nbd.com.cn/articles/2024-10-21/3597978.html"
    },
    {
        "title": "控股股东“尝鲜”股票回购增持贷款 玲珑轮胎：从行业和企业层面，这个算中性消息",
        "time": "2024-10-21 15:46:10",
        "url": "https://www.nbd.com.cn/articles/2024-10-21/3597989.html"
    },
    {
        "title": "imec 牵头组建汽车芯粒计划，Arm、宝马集团、博世等巨头首批承诺加入",
        "time": "2024-10-21 15:49:40",
        "url": "https://www.ithome.com/0/803/907.htm"
    },
    {
        "title": "比亚迪唐 L SUV 车型无伪装前脸曝光：采用分体式大灯、同步家族式设计",
        "time": "2024-10-21 15:50:30",
        "url": "https://www.ithome.com/0/803/908.htm"
    },
    {
        "title": "京东在珠海成立贸易公司，含新能源汽车整车销售业务",
        "time": "2024-10-21 15:50:44",
        "url": "https://www.ithome.com/0/803/909.htm"
    },
    {
        "title": "上周政策利好频出，债券基金涨幅普遍扩大，货币宽松环境持续支撑市场",
        "time": "2024-10-21 15:51:29",
        "url": "https://www.nbd.com.cn/articles/2024-10-21/3597999.html"
    },
    {
        "title": "OPPO 全家桶照片公布，含 Find X8 系列手机、Pad3 Pro 平板等",
        "time": "2024-10-21 15:52:28",
        "url": "https://www.ithome.com/0/803/910.htm"
    }
]