[
    {
        "title": "被国际刑警组织发红色通缉令，韩财阀千金被曝已逃至柬埔寨，知情人士：她为电诈园区洗",
        "time": "2025-10-17 18:14:35",
        "url": "https://www.nbd.com.cn/articles/2025-10-17/4095548.html"
    },
    {
        "title": "iPhone Air开售，首批5分钟售罄！仅A3518机型可在中国大陆激活，eSIM可沿用实体卡的号",
        "time": "2025-10-17 18:14:24",
        "url": "https://www.nbd.com.cn/articles/2025-10-17/4095547.html"
    },
    {
        "title": "集体跳水！黑色星期五来袭，全球股市下挫，加密货币市场超30万人爆仓，金价拉升",
        "time": "2025-10-17 18:14:00",
        "url": "https://www.nbd.com.cn/articles/2025-10-17/4095546.html"
    },
    {
        "title": "【美股盘前】美国两家银行“爆雷”，大型银行股普跌；加密货币概念股、科技股普跌；礼",
        "time": "2025-10-17 18:11:50",
        "url": "https://www.nbd.com.cn/articles/2025-10-17/4095481.html"
    },
    {
        "title": "浙江宣传部部长赵承：去年《黑神话：悟空》全球销售量超 2800 万，销售额达 90 亿元",
        "time": "2025-10-17 18:11:36",
        "url": "https://www.ithome.com/0/890/333.htm"
    },
    {
        "title": "饿了么公布期权回购方案",
        "time": "2025-10-17 18:10:54",
        "url": "https://www.jiemian.com/article/13479780.html"
    },
    {
        "title": "小米 REDMI K90 Pro Max 真机图曝光，10 月 23 日发布",
        "time": "2025-10-17 18:08:33",
        "url": "https://www.ithome.com/0/890/332.htm"
    },
    {
        "title": "红魔氘锋能量魔块 10000mAh 发布：PD 45W 快充、提手式快充线，首发 169 元",
        "time": "2025-10-17 18:04:45",
        "url": "https://www.ithome.com/0/890/331.htm"
    },
    {
        "title": "爱马仕男装艺术总监Véronique Nichanian将离任",
        "time": "2025-10-17 18:04:14",
        "url": "https://www.jiemian.com/article/13479735.html"
    },
    {
        "title": "可适配燃油车型！博世量产交付中阶智驾方案，高阶智驾方案今年内将量产",
        "time": "2025-10-17 18:01:16",
        "url": "https://www.nbd.com.cn/articles/2025-10-17/4095327.html"
    },
    {
        "title": "台积电加速在美后续晶圆厂建设、在日第二晶圆厂动工",
        "time": "2025-10-17 18:01:14",
        "url": "https://www.ithome.com/0/890/330.htm"
    },
    {
        "title": "库克来华，为何频频造访文创企业？",
        "time": "2025-10-17 17:59:43",
        "url": "https://www.nbd.com.cn/articles/2025-10-17/4095531.html"
    },
    {
        "title": "泽连斯基会见美国军火公司代表！乌克兰多地实施紧急断电，全国工业用户遭限电",
        "time": "2025-10-17 17:55:04",
        "url": "https://www.nbd.com.cn/articles/2025-10-17/4095508.html"
    },
    {
        "title": "499 元起 vivo WATCH GT 2 手表开售，2400nits 高亮高刷屏",
        "time": "2025-10-17 17:54:00",
        "url": "https://tech.ifeng.com/c/8nWs7SkhBTR"
    },
    {
        "title": "中海基金老牌投资高管“卸任”，许定晴卸任总助转任CIO",
        "time": "2025-10-17 17:51:37",
        "url": "https://wallstreetcn.com/articles/3757392"
    },
    {
        "title": "OPPO Find X9 Pro深度体验评测：2亿哈苏，装进口袋",
        "time": "2025-10-17 17:51:12",
        "url": "https://tech.ifeng.com/c/8nWs7SkhBTQ"
    },
    {
        "title": "玩家吐槽《战地6》游戏光影效果，从室内看室外时就像遇到闪光弹",
        "time": "2025-10-17 17:51:00",
        "url": "https://tech.ifeng.com/c/8nWs7SkhBTP"
    },
    {
        "title": "66 亿元人民币买楼，阿里与蚂蚁联合投资设立香港总部",
        "time": "2025-10-17 17:34:10",
        "url": "https://tech.ifeng.com/c/8nWqUirxrO7"
    },
    {
        "title": "Meta 和 Oracle 将为 AIDC 导入英伟达 Spectrum-X 以太网交换机",
        "time": "2025-10-17 17:32:39",
        "url": "https://tech.ifeng.com/c/8nWqa45rSlO"
    },
    {
        "title": "499 元起 vivo WATCH GT 2 手表开售，2400nits 高亮高刷屏 + 全天候健康检测",
        "time": "2025-10-17 17:54:31",
        "url": "https://www.ithome.com/0/890/329.htm"
    },
    {
        "title": "习酒发布电商“避坑”指南：公布超200家“正规”店铺，新增即时零售渠道",
        "time": "2025-10-17 17:51:46",
        "url": "https://www.nbd.com.cn/articles/2025-10-17/4095450.html"
    },
    {
        "title": "【IT之家评测室】OPPO Find X9 Pro 深度体验：2 亿哈苏，装进口袋",
        "time": "2025-10-17 17:51:12",
        "url": "https://www.ithome.com/0/890/328.htm"
    },
    {
        "title": "玩家吐槽《战地 6》游戏光影效果，从室内看室外时就像遇到闪光弹",
        "time": "2025-10-17 17:51:00",
        "url": "https://www.ithome.com/0/890/327.htm"
    },
    {
        "title": "一波多折，蔚来御用激光雷达公司图达通，终于快要上市了",
        "time": "2025-10-17 17:44:09.190000",
        "url": "https://36kr.com/p/3513059640368262"
    },
    {
        "title": "中交集团签约中交三航局AI应用场景建设项目",
        "time": "2025-10-17 17:40:52",
        "url": "https://www.jiemian.com/article/13479671.html"
    },
    {
        "title": "微软全面升级Windows 11，语音成为核心交互方式",
        "time": "2025-10-17 17:36:55",
        "url": "https://36kr.com/p/3513006807554950"
    },
    {
        "title": "66 亿元人民币铜锣湾买楼，阿里与蚂蚁联合投资设立香港总部",
        "time": "2025-10-17 17:34:10",
        "url": "https://www.ithome.com/0/890/325.htm"
    },
    {
        "title": "安徽省能源集团原党委书记、总经理方平接受审查调查",
        "time": "2025-10-17 17:32:41",
        "url": "https://www.jiemian.com/article/13479626.html"
    },
    {
        "title": "Meta 和 Oracle 将为 AI 数据中心导入英伟达 Spectrum-X 以太网交换机",
        "time": "2025-10-17 17:32:39",
        "url": "https://www.ithome.com/0/890/324.htm"
    },
    {
        "title": "红魔氘锋 80W 桌面风冷无线充电座发布：自适应风冷散热，首发 399 元",
        "time": "2025-10-17 17:31:55",
        "url": "https://www.ithome.com/0/890/323.htm"
    },
    {
        "title": "硬刚 Sora 2，谷歌的 Veo 3.1 确实有小惊喜",
        "time": "2025-10-17 17:31:22.379000",
        "url": "https://36kr.com/p/3513005569956998"
    },
    {
        "title": "阿里巴巴与蚂蚁联合投资设立香港总部，立足中国面向全球",
        "time": "2025-10-17 17:30:45",
        "url": "https://www.jiemian.com/article/13479617.html"
    },
    {
        "title": "前《刺客信条》负责人科特发声：并未主动辞职，而是被育碧要求让位",
        "time": "2025-10-17 17:29:23",
        "url": "https://www.ithome.com/0/890/322.htm"
    },
    {
        "title": "前《刺客信条》负责人发声：被育碧要求让位，而非主动辞职",
        "time": "2025-10-17 17:29:00",
        "url": "https://tech.ifeng.com/c/8nWpTinaWN9"
    },
    {
        "title": "倍思成为 2025 可持续全球领导者大会指定移动电源品牌",
        "time": "2025-10-17 17:28:11",
        "url": "https://tech.ifeng.com/c/8nWpYtGiNC1"
    },
    {
        "title": "倍思成为 2025 可持续全球领导者大会指定移动电源品牌",
        "time": "2025-10-17 17:28:11",
        "url": "https://www.ithome.com/0/890/321.htm"
    },
    {
        "title": "别克回应至境 L7 宁德时代和江苏正力电池区别",
        "time": "2025-10-17 17:22:59",
        "url": "https://tech.ifeng.com/c/8nWpTinaWN8"
    },
    {
        "title": "别克回应至境 L7 宁德时代和江苏正力电池区别：都符合奥特能 2.0 标准",
        "time": "2025-10-17 17:22:59",
        "url": "https://www.ithome.com/0/890/318.htm"
    },
    {
        "title": "美团开源LongCat-Audio-Codec",
        "time": "2025-10-17 17:18:46",
        "url": "https://www.jiemian.com/article/13479503.html"
    },
    {
        "title": "2025 世界智能网联汽车大会第二天：市场监管总局将加强智能网联汽车产品准入、召回和软件在线升级管理等要求",
        "time": "2025-10-17 17:14:52",
        "url": "https://www.ithome.com/0/890/311.htm"
    },
    {
        "title": "美国区域银行再陷危机，高盛直呼“太疯狂”，这是客户最关心的三个问题！",
        "time": "2025-10-17 17:14:20",
        "url": "https://wallstreetcn.com/articles/3757390"
    },
    {
        "title": "大厂投资的女总裁敲钟了，开盘冲到近100亿",
        "time": "2025-10-17 17:11:41.380000",
        "url": "https://36kr.com/p/3512996783692162"
    },
    {
        "title": "中国信通院：2025 年 7 月国内手机市场出货量 2809.3 万部",
        "time": "2025-10-17 17:10:47",
        "url": "https://tech.ifeng.com/c/8nWoPvGsiII"
    },
    {
        "title": "中国信通院：2025 年 7 月国内手机市场出货量 2809.3 万部，同比增长 16.1%",
        "time": "2025-10-17 17:10:47",
        "url": "https://www.ithome.com/0/890/307.htm"
    },
    {
        "title": "2025年，AI眼镜走下神坛",
        "time": "2025-10-17 17:10:29.942000",
        "url": "https://36kr.com/p/3512995092749189"
    },
    {
        "title": "2025 年度英伟达中国开发者日活动将于 11 月 14 日在苏州举行",
        "time": "2025-10-17 17:09:50",
        "url": "https://tech.ifeng.com/c/8nWnv3sI50m"
    },
    {
        "title": "2025 年度英伟达中国开发者日活动将于 11 月 14 日在苏州举行",
        "time": "2025-10-17 17:09:50",
        "url": "https://www.ithome.com/0/890/306.htm"
    },
    {
        "title": "Calibre 8.13更新，让虚拟书库搜索更智能",
        "time": "2025-10-17 17:09:17",
        "url": "https://tech.ifeng.com/c/8nWoPvGsiE1"
    },
    {
        "title": "开源电子书管家 Calibre 更新 8.13 版：更新虚拟书库搜索方式，支持 Windows API 启动外部程序",
        "time": "2025-10-17 17:09:17",
        "url": "https://www.ithome.com/0/890/305.htm"
    },
    {
        "title": "“天才”与“疯子”的双生样本：蒋凡向左，无招向右",
        "time": "2025-10-17 17:08:30.794000",
        "url": "https://36kr.com/p/3512983022180484"
    }
]