[
    {
        "title": "比亚迪 e7 官图公布：定位中级纯电轿车，拥有 2820mm 超长轴距",
        "time": "2025-04-09 15:32:30",
        "url": "https://www.ithome.com/0/844/016.htm"
    },
    {
        "title": "起亚下调2030年电动汽车销售目标",
        "time": "2025-04-09 15:32:07",
        "url": "https://www.jiemian.com/article/12587183.html"
    },
    {
        "title": "八年磨一剑：《愤怒小鸟 3》大电影定档 2027 年 1 月 29 日",
        "time": "2025-04-09 15:30:54",
        "url": "https://www.ithome.com/0/844/014.htm"
    },
    {
        "title": "腾讯张军回应“已读”功能：一开始微信就坚定不移地不提供这个功能，以后也不会",
        "time": "2025-04-09 15:28:43",
        "url": "https://www.ithome.com/0/844/013.htm"
    },
    {
        "title": "ETF今日收评 | 500ETF增强涨超9%，高端装备ETF、国防ETF、军工龙头ETF涨超6%",
        "time": "2025-04-09 15:27:57",
        "url": "https://www.nbd.com.cn/articles/2025-04-09/3824378.html"
    },
    {
        "title": "中美经贸关系中方立场白皮书：要尊重彼此核心利益和重大关切，通过对话协商找到妥善解决问题的办法",
        "time": "2025-04-09 15:27:13",
        "url": "https://wallstreetcn.com/articles/3744878"
    },
    {
        "title": "广汽丰田宣布凯美瑞智驾版上市",
        "time": "2025-04-09 15:26:37",
        "url": "https://www.jiemian.com/article/12587111.html"
    },
    {
        "title": "世界互联网大会亚太峰会首度在港举办，香港数字政策专员：强化港国际创科中心地位",
        "time": "2025-04-09 15:24:04",
        "url": "https://tech.ifeng.com/c/8iPfUJ6dDuG"
    },
    {
        "title": "38.5 → 1.5 小时：Frontier 超算刷新计算流体力学速度纪录，模拟时间减少 96%",
        "time": "2025-04-09 15:22:26",
        "url": "https://www.ithome.com/0/844/011.htm"
    },
    {
        "title": "一级能耗新能源车来了 小鹏P7+与MONA M03获首批认证",
        "time": "2025-04-09 15:21:22",
        "url": "https://tech.ifeng.com/c/8iPfYScma7K"
    },
    {
        "title": "CF Industries与JERA和三井物产成立合资企业，将投资40亿美元建低碳氨工厂",
        "time": "2025-04-09 15:20:58",
        "url": "https://www.jiemian.com/article/12587078.html"
    },
    {
        "title": "东兴证券：停止新开投资者“单客户多银行”辅资金账户",
        "time": "2025-04-09 15:20:50",
        "url": "https://www.jiemian.com/article/12587068.html"
    },
    {
        "title": "贝索斯秘密打造“人人买得起的车”：有钱可烧，不复制特斯拉",
        "time": "2025-04-09 15:19:58",
        "url": "https://www.ithome.com/0/844/010.htm"
    },
    {
        "title": "AH股午后拉升！A股全天放量大涨，军工股掀涨停潮，恒科指涨3%，南向资金净买入额创纪录新高",
        "time": "2025-04-09 15:19:35",
        "url": "https://wallstreetcn.com/articles/3744860"
    },
    {
        "title": "文远知行宣布采用BlackBerry QNX系统",
        "time": "2025-04-09 15:18:01",
        "url": "https://www.jiemian.com/article/12587040.html"
    },
    {
        "title": "悦达起亚一季度销量同比增长13%",
        "time": "2025-04-09 15:16:01",
        "url": "https://www.jiemian.com/article/12587016.html"
    },
    {
        "title": "铁威马推出 D9-320 九盘位硬盘柜：每盘位独立电源开关，USB 10Gbps 传输",
        "time": "2025-04-09 15:15:41",
        "url": "https://www.ithome.com/0/844/008.htm"
    },
    {
        "title": "孪生世界动态仿真新突破，北大发布RainyGS：降雨/洪涝/风速精准可控",
        "time": "2025-04-09 15:14:10.938000",
        "url": "https://36kr.com/p/3242546570296967"
    },
    {
        "title": "东风柳汽试验中心法规标准专业三级首席师何毅波接受审查调查",
        "time": "2025-04-09 15:13:15",
        "url": "https://www.jiemian.com/article/12587012.html"
    },
    {
        "title": "美方认为巨额贸易逆差让美国“吃亏”，商务部回应",
        "time": "2025-04-09 15:11:12",
        "url": "https://wallstreetcn.com/articles/3744881"
    },
    {
        "title": "通用技术集团：积极开展并购重组，有序推进相关上市公司股票回购",
        "time": "2025-04-09 15:10:19",
        "url": "https://www.jiemian.com/article/12586964.html"
    },
    {
        "title": "贵州燃气拟并购控股股东名下资产  标的公司4月23日有庭审",
        "time": "2025-04-09 15:09:53",
        "url": "https://www.nbd.com.cn/articles/2025-04-08/3823275.html"
    },
    {
        "title": "vivo 再度重组 AI 部门，明确新架构与职责",
        "time": "2025-04-09 15:09:44",
        "url": "https://www.pingwest.com/w/303780"
    },
    {
        "title": "嘀嗒顺风车回应司机高速上开辅助驾驶剪指甲：车主账号已被封禁",
        "time": "2025-04-09 15:09:22",
        "url": "https://www.ithome.com/0/844/007.htm"
    },
    {
        "title": "特朗普关税冲击美电商巨头 亚马逊开始“压榨”供应商",
        "time": "2025-04-09 15:09:13",
        "url": "https://tech.ifeng.com/c/8iPeeH7AMZ3"
    },
    {
        "title": "强生完成对Intra-Cellular Therapies收购",
        "time": "2025-04-09 15:08:24",
        "url": "https://www.jiemian.com/article/12586944.html"
    },
    {
        "title": "美股期货转涨，欧股跌幅收窄，30年美债收益率一度上行25个基点，黄金大涨超2%",
        "time": "2025-04-09 15:06:44",
        "url": "https://wallstreetcn.com/articles/3744867"
    },
    {
        "title": "140亿元，兖矿能源欲溢价拿下西北矿业控股权 “同业竞争”能否破局？",
        "time": "2025-04-09 15:05:38",
        "url": "https://www.nbd.com.cn/articles/2025-04-09/3824321.html"
    },
    {
        "title": "红魔姜超：Air 是在原有旗舰基础上新增一个系列，面向年轻玩家普及游戏科技",
        "time": "2025-04-09 14:59:17",
        "url": "https://www.ithome.com/0/844/003.htm"
    },
    {
        "title": "泰坦尼克号残骸高清扫描首次公开：71.5 万张照片、16TB 数据",
        "time": "2025-04-09 14:58:55",
        "url": "https://www.ithome.com/0/844/002.htm"
    },
    {
        "title": "柒和伊控股：2025财年回购至多6000亿日元股票",
        "time": "2025-04-09 14:57:59",
        "url": "https://www.jiemian.com/article/12586818.html"
    },
    {
        "title": "五粮液大股东拟掷不超过10亿元增持，贵州茅台加速回购，机构称白酒板块底部信号隐现",
        "time": "2025-04-09 14:57:54",
        "url": "https://www.nbd.com.cn/articles/2025-04-09/3824305.html"
    },
    {
        "title": "赛道Hyper | 海油工程：自带深海科技应用龙头气质",
        "time": "2025-04-09 14:46:01",
        "url": "https://wallstreetcn.com/articles/3744877"
    },
    {
        "title": "微博创作者中心：个人账号单日发布超 50 条内容后将作限流处理",
        "time": "2025-04-09 14:55:37",
        "url": "https://www.ithome.com/0/844/001.htm"
    },
    {
        "title": "元戎启行联合高通基于骁龙平台发布高阶智驾，涵盖激光雷达和纯视觉方案",
        "time": "2025-04-09 14:54:47",
        "url": "https://www.ithome.com/0/844/000.htm"
    },
    {
        "title": "广州市商务局：希音国内供应链持续加码布局",
        "time": "2025-04-09 14:49:41",
        "url": "https://www.jiemian.com/article/12586793.html"
    },
    {
        "title": "谷歌展示AR眼镜原型：Gemini加持，支持实时翻译",
        "time": "2025-04-09 14:49:00",
        "url": "https://tech.ifeng.com/c/8iPcCUhPQBC"
    },
    {
        "title": "阿里云发布 “繁花”计划，并推出AI应用与服务市场",
        "time": "2025-04-09 14:48:17",
        "url": "https://www.pingwest.com/w/303779"
    },
    {
        "title": "《哪吒2》，票房破156亿元！日本知名导演看完直呼：超出想象100倍，日本动漫危险了！日",
        "time": "2025-04-09 14:47:09",
        "url": "https://www.nbd.com.cn/articles/2025-04-09/3824307.html"
    },
    {
        "title": "按专业相机思路做手机，消息称 vivo X200 Ultra 支持「外挂镜头」",
        "time": "2025-04-09 14:46:39",
        "url": "https://www.ithome.com/0/843/999.htm"
    },
    {
        "title": "全国首个，深开鸿发布基于开源鸿蒙的机器人操作系统 M-Robots OS",
        "time": "2025-04-09 14:45:47",
        "url": "https://www.ithome.com/0/843/998.htm"
    },
    {
        "title": "特朗普的灾难性败局开始显现：美债利率飙升",
        "time": "2025-04-09 14:44:40",
        "url": "https://wallstreetcn.com/articles/3744874"
    },
    {
        "title": "UALink 200G 1.0 规范发布，支持 1024 个加速器互联",
        "time": "2025-04-09 14:42:58",
        "url": "https://www.ithome.com/0/843/996.htm"
    },
    {
        "title": "比亚迪已向宋L系列车型推送哨兵模式、千里眼功能",
        "time": "2025-04-09 14:41:18",
        "url": "https://tech.ifeng.com/c/8iPcU3BPFjT"
    },
    {
        "title": "意识是怎么来的，我国科研人员尝试破解",
        "time": "2025-04-09 14:40:32",
        "url": "https://www.ithome.com/0/843/995.htm"
    },
    {
        "title": "优派发布 M1 Max 便携投影仪：打造随身影院",
        "time": "2025-04-09 14:39:44",
        "url": "https://www.ithome.com/0/843/994.htm"
    },
    {
        "title": "易华录与海纳医信达成战略合作",
        "time": "2025-04-09 14:38:26",
        "url": "https://www.jiemian.com/article/12586671.html"
    },
    {
        "title": "vivo X200 Ultra 手机预告：蔡司三大定焦大师镜头、全新相机控制键",
        "time": "2025-04-09 14:35:25",
        "url": "https://www.ithome.com/0/843/993.htm"
    },
    {
        "title": "问界M8定档4月16日上市",
        "time": "2025-04-09 14:35:15",
        "url": "https://tech.ifeng.com/c/8iPcH7ybRn2"
    },
    {
        "title": "尚颀资本领投崇辉半导体B轮融资",
        "time": "2025-04-09 14:34:49",
        "url": "https://www.jiemian.com/article/12586652.html"
    }
]